technical_indicators/AUTHORS.txt
technical_indicators/ChangeLog.txt
technical_indicators/LICENSE.txt
technical_indicators/README.txt
technical_indicators/technical_indicators.py
technical_indicators/__init__.py
technical_indicators/doc/.buildinfo
technical_indicators/doc/changelog.html
technical_indicators/doc/codeauthors.html
technical_indicators/doc/genindex.html
technical_indicators/doc/index.html
technical_indicators/doc/license.html
technical_indicators/doc/objects.inv
technical_indicators/doc/py-modindex.html
technical_indicators/doc/reference.html
technical_indicators/doc/search.html
technical_indicators/doc/searchindex.js
technical_indicators/doc/technical_indicators.pdf
technical_indicators/doc/_modules/index.html
technical_indicators/doc/_modules/technical_indicators/technical_indicators.html
technical_indicators/doc/_sources/changelog.txt
technical_indicators/doc/_sources/codeauthors.txt
technical_indicators/doc/_sources/index.txt
technical_indicators/doc/_sources/license.txt
technical_indicators/doc/_sources/reference.txt
technical_indicators/doc/_static/ajax-loader.gif
technical_indicators/doc/_static/basic.css
technical_indicators/doc/_static/comment-bright.png
technical_indicators/doc/_static/comment-close.png
technical_indicators/doc/_static/comment.png
technical_indicators/doc/_static/default.css
technical_indicators/doc/_static/doctools.js
technical_indicators/doc/_static/down-pressed.png
technical_indicators/doc/_static/down.png
technical_indicators/doc/_static/file.png
technical_indicators/doc/_static/jquery.js
technical_indicators/doc/_static/minus.png
technical_indicators/doc/_static/plus.png
technical_indicators/doc/_static/pygments.css
technical_indicators/doc/_static/searchtools.js
technical_indicators/doc/_static/sidebar.js
technical_indicators/doc/_static/underscore.js
technical_indicators/doc/_static/up-pressed.png
technical_indicators/doc/_static/up.png
technical_indicators-0.0.13.dist-info/DESCRIPTION.rst
technical_indicators-0.0.13.dist-info/entry_points.txt
technical_indicators-0.0.13.dist-info/METADATA
technical_indicators-0.0.13.dist-info/pydist.json
technical_indicators-0.0.13.dist-info/RECORD
technical_indicators-0.0.13.dist-info/top_level.txt
technical_indicators-0.0.13.dist-info/WHEEL
